Workbook

Sheet README
A1: US/UK expat tax workbook — US tax year 2025 / UK tax year 2025-26
A3: Cell convention: BLUE = your inputs GREY = year constants (verify!) WHITE = calculated
A5: This is an estimation scaffold, not tax software. Grey constants were entered from 2025
A6: figures known at generation time — verify each against the corpus (`usuk ask ...`) or the
A7: official instructions before relying on a number.
A9: Sheets:
A10: FX — exchange rates (IRS yearly average for the US return; HMRC rates for SA)
A11: Employment — UK salary + PAYE from P60/payslips, converted to USD
A12: Options — per-exercise/vest rows with US/UK workday apportionment
A13: Rental — UK property: parallel UK (SA105) and US (Schedule E + ADS depreciation) computations
A14: UK Tax — rough UK 2025-26 liability (England bands; PAYE-adjusted)
A15: US FTC — Form 1116 general-basket limitation and excess-credit position
... A21: Not professional advice — verify high-stakes positions with a cross-border professional.

Sheet FX
A1: Exchange rates
A2: IRS yearly average 2025 (GBP per 1 USD) | B2: 0.759 | C2: irs.gov 'Yearly average currency exchange rates' — use for US return income
A3: IRS yearly average 2024 (GBP per 1 USD) | B3: 0.783 | C3: for reference / prior-year items
A4: Spot rate override (GBP per 1 USD), optional | C4: specific-transaction rate (e.g. option exercise date) if you prefer spot for that item
A5: USD = GBP / rate. UK SA is computed in GBP directly (no conversion needed).

Sheet Employment
A1: UK employment income (P60 / final 2025 payslips)
C2: US return needs CALENDAR-2025 amounts; UK SA needs 2025-26 amounts. Enter both — payslips are the bridge.
A3: Gross pay, calendar 2025 (GBP) | C3: sum Jan-Dec 2025 payslips
A4: UK tax (PAYE) withheld, calendar 2025 (GBP) | C4: accrued/paid basket choice on Form 1116 — be consistent
A5: Gross pay, UK year 2025-26 (GBP) | C5: P60 for 2025-26
A6: UK tax (PAYE) withheld, 2025-26 (GBP)
A7: Employee NIC, 2025-26 (GBP) | C7: NIC is NOT creditable as income tax on Form 1116
A9: Gross pay, calendar 2025 (USD) | B9: =IF(B3>0,B3/FX!$B$2,0)
A10: UK tax withheld, calendar 2025 (USD) | B10: =IF(B4>0,B4/FX!$B$2,0)

Sheet Options
A1: Equity compensation — one row per taxable event (NQSO exercise / RSU vest / ISO exercise)
A2: Sourcing: spread is apportioned by workdays over grant→vest. UK workday share taxed by UK (usually via PAYE, see EIM43501/ERSM162000); total spread is US-taxable (citizen) with FTC for the UK share. ISO exercises: no regular-tax spread but AMT adjustment (Form 6251).
A4: Grant/award ID | B4: Type | C4: Grant date | D4: Vest/exercise date | E4: Shares | F4: Strike $ | G4: FMV $ | H4: Spread $ (calc) | I4: Days grant→vest | J4: UK workdays | K4: UK share (calc) | L4: UK-source $ (calc) | M4: US-source $ (calc)
H5: =IF(E5>0,E5*(G5-F5),0) | K5: =IF(I5>0,J5/I5,0) | L5: =H5*K5 | M5: =H5-L5
H6: =IF(E6>0,E6*(G6-F6),0) | K6: =IF(I6>0,J6/I6,0) | L6: =H6*K6 | M6: =H6-L6
H7: =IF(E7>0,E7*(G7-F7),0) | K7: =IF(I7>0,J7/I7,0) | L7: =H7*K7 | M7: =H7-L7
H8: =IF(E8>0,E8*(G8-F8),0) | K8: =IF(I8>0,J8/I8,0) | L8: =H8*K8 | M8: =H8-L8
H9: =IF(E9>0,E9*(G9-F9),0) | K9: =IF(I9>0,J9/I9,0) | L9: =H9*K9 | M9: =H9-L9
H10: =IF(E10>0,E10*(G10-F10),0) | K10: =IF(I10>0,J10/I10,0) | L10: =H10*K10 | M10: =H10-L10
H11: =IF(E11>0,E11*(G11-F11),0) | K11: =IF(I11>0,J11/I11,0) | L11: =H11*K11 | M11: =H11-L11
H12: =IF(E12>0,E12*(G12-F12),0) | K12: =IF(I12>0,J12/I12,0) | L12: =H12*K12 | M12: =H12-L12
H13: =IF(E13>0,E13*(G13-F13),0) | K13: =IF(I13>0,J13/I13,0) | L13: =H13*K13 | M13: =H13-L13
H14: =IF(E14>0,E14*(G14-F14),0) | K14: =IF(I14>0,J14/I14,0) | L14: =H14*K14 | M14: =H14-L14
G15: Totals: | H15: =SUM(H5:H14) | L15: =SUM(L5:L14) | M15: =SUM(M5:M14)
A17: UK tax paid via PAYE on option/RSU income, calendar 2025 (GBP):

Sheet Rental
A1: UK rental property — parallel computations
A2: UK column: 2025-26 amounts, SA105 rules (no depreciation; finance-cost 20% credit). US column: calendar-2025 amounts in GBP (converted below), Schedule E rules (depreciation; full mortgage interest).
B4: UK 2025-26 (GBP) | C4: US cal-2025 (GBP)
A5: Rents received
A6: Letting agent fees
A7: Repairs and maintenance (not improvements)
A8: Insurance
A9: Other allowable expenses
A10: Mortgage interest (finance costs) | D10: UK: NOT deducted here — 20% credit below. US: fully deductible.
A11: UK property profit (excl. finance costs) | B11: =B5-SUM(B6:B9) | C11: → SA105
A12: UK finance-cost tax credit (20%) | B12: =0.2*B10 | C12: reduces UK tax, not profit
A14: US depreciable basis (building only, USD) | C14: lower of cost or FMV when first rented, excl. land; foreign residential = 30-yr ADS straight line
A15: US annual depreciation (30-yr ADS) | B15: =B14/30
A16: US Schedule E net income (USD) | B16: =(C5-SUM(C6:C10))/FX!$B$2-B15 | C16: rents less ALL expenses incl. interest, less depreciation

Sheet UK Tax
A1: UK 2025-26 liability estimate (England/NI bands)
A2: Personal allowance | B2: 12570 | C2: tapered £1 per £2 of income over £100,000
A3: Basic-rate band (20%) | B3: 37700
A4: Additional-rate threshold (45%) | B4: 125140
A6: Employment income 2025-26 | B6: =Employment!B5
A7: Property profit | B7: ='Rental'!B11
A8: Other UK-taxable income (interest, dividends...) | C8: model dividend rates separately if material
A9: Total income | B9: =SUM(B6:B8)
A10: Personal allowance (after taper) | B10: =MAX(0,B2-MAX(0,(B9-100000)/2))
A11: Taxable income | B11: =MAX(0,B9-B10)
A12: Tax at 20% / 40% / 45% | B12: =0.2*MIN(B11,B3)+0.4*MAX(0,MIN(B11,B4-B2)-B3)+0.45*MAX(0,B11-(B4-B2)) | C12: approximation — bands shift with pension/gift-aid contributions
A13: Less: finance-cost credit (rental) | B13: ='Rental'!B12
A14: Estimated UK liability | B14: =MAX(0,B12-B13)
A15: Less: PAYE paid 2025-26 | B15: =Employment!B6
A16: Balancing payment due 31 Jan 2027 (est.) | B16: =B14-B15

Sheet US FTC
A1: Form 1116 — general category limitation (calendar 2025, USD)
A2: Standard deduction (MFJ, 2025) | B2: 31500 | C2: verify in i1040; itemize instead if better
A4: Foreign-source wages | B4: =Employment!B9
A5: Foreign-source option/RSU income (UK share) | B5: =Options!L15 | C5: US-workday share is US-source and NOT in the FTC numerator
A6: Foreign-source rental net income | B6: ='Rental'!B16 | C6: passive basket if net positive — see note
A7: Foreign-source taxable income (FSTI) | B7: =SUM(B4:B6)
A8: US-source income (US option share, US interest...)
A9: Total taxable income before deduction | B9: =B7+B8
A10: Taxable income (after standard deduction) | B10: =MAX(0,B9-B2)
A11: US tax before credits (from 1040 tables on line above) | C11: compute from 2025 MFJ brackets; then subtract CTC/ODC AFTER the FTC per form ordering
A12: FTC limitation = US tax × FSTI / TI | B12: =IF(B10>0,B11*MIN(1,B7/B10),0)
A13: UK tax paid/accrued on that income (USD) | B13: =Employment!B10+IF(Options!C17>0,Options!C17/FX!$B$2,0) | C13: employment PAYE + option PAYE; add UK tax on rental when SA is finalised
A14: Credit usable this year | B14: =MIN(B12,B13)
A15: Excess (carryback 1 yr / carryforward 10 yrs) | B15: =MAX(0,B13-B12)
A17: Note: net rental income is usually PASSIVE basket (separate 1116). UK tax rates exceed US rates, so high-taxed passive income may kick back to general — model when figures are real.

Sheet FEIE vs FTC
A1: Strategy comparison — decide with real numbers
A2: FEIE limit per spouse (2025) | B2: 130000 | C2: verify in i2555
B4: A: FTC only | C4: B: FEIE + FTC
A5: Earned income covered | B5: credit for UK tax | C5: excluded up to limit
A6: Child Tax Credit (refundable ACTC) | B6: available | C6: LOST if income fully excluded — often decisive with 2-3 qualifying kids
A7: Unexcluded income tax rate | B7: n/a | C7: stacking rule: taxed at higher brackets
A8: Carryovers build up | B8: yes (10-yr carryforward) | C8: no carryover on excluded income
A9: Revocation trap | B9: none | C9: revoking FEIE bars re-election for 5 years without IRS consent
A10: Typical outcome, high UK tax + kids + rental | B10: usually better | C10: rarely better
A12: UK marginal rates (20/40/45%) generally exceed US rates, so the FTC usually wipes out US tax on UK earnings AND preserves the refundable Child Tax Credit. Verify by filling both scenarios once real numbers exist.
